pycsmeter-0.0.1.dist-info/METADATA
pycsmeter-0.0.1.dist-info/WHEEL
pycsmeter-0.0.1.dist-info/entry_points.txt
pycsmeter-0.0.1.dist-info/licenses/LICENSE
pycsmeter/__init__.py
pycsmeter/_packets.py
pycsmeter/cli.py
pycsmeter/exceptions.py
pycsmeter/valve.py
pycsmeter-0.0.1.dist-info/RECORD
