Metadata-Version: 2.4
Name: pycsmeter
Version: 0.0.1
Summary: Python API for CS Meter Water Softner
Author-Email: Patrik Torstensson <patrik.torstensson@gmail.com>
License-Expression: MIT
License-File: LICENSE
Classifier: Development Status :: 4 - Beta
Classifier: Intended Audience :: Developers
Classifier: Programming Language :: Python
Classifier: Programming Language :: Python :: 3
Classifier: Programming Language :: Python :: 3 :: Only
Classifier: Programming Language :: Python :: 3.9
Classifier: Programming Language :: Python :: 3.10
Classifier: Programming Language :: Python :: 3.11
Classifier: Programming Language :: Python :: 3.12
Classifier: Programming Language :: Python :: 3.13
Classifier: Programming Language :: Python :: 3.14
Classifier: Topic :: Documentation
Classifier: Topic :: Software Development
Classifier: Topic :: Utilities
Classifier: Typing :: Typed
Project-URL: Homepage, https://ptorsten.github.io/pycsmeter
Project-URL: Documentation, https://ptorsten.github.io/pycsmeter
Project-URL: Changelog, https://ptorsten.github.io/pycsmeter/changelog
Project-URL: Repository, https://github.com/ptorsten/pycsmeter
Project-URL: Issues, https://github.com/ptorsten/pycsmeter/issues
Project-URL: Discussions, https://github.com/ptorsten/pycsmeter/discussions
Project-URL: Gitter, https://gitter.im/pycsmeter/community
Project-URL: Funding, https://github.com/sponsors/ptorsten
Requires-Python: >=3.9
Requires-Dist: bleak>=0.22.3
Requires-Dist: click>=8.1.8
Requires-Dist: pytest-asyncio>=1.0.0
Requires-Dist: setuptools>=80.8.0
Requires-Dist: tabulate>=0.9.0
Requires-Dist: types-tabulate>=0.9.0.20241207
Provides-Extra: dev
Requires-Dist: pytest>=7.0.0; extra == "dev"
Requires-Dist: pytest-asyncio>=0.21.0; extra == "dev"
Requires-Dist: pytest-cov>=4.0.0; extra == "dev"
Requires-Dist: pytest-mock>=3.10.0; extra == "dev"
